sunpeek_exampledata/FHW__array_ArcS__2017-01-01__2017-12-31__1m__UTC.csv
sunpeek_exampledata/FHW__array_ArcS__2017-05-01__2017-05-02__1m__UTC.csv
sunpeek_exampledata/FHW__array_ArcS__2017-05-01__2017-05-31__1m__UTC.csv
"sunpeek_exampledata/Pekasolar, pdf export, density.csv"
"sunpeek_exampledata/Pekasolar, pdf export, heat capacity.csv"
sunpeek_exampledata/__init__.py
sunpeek_exampledata/plant_config_FHW_Arcon_South.json
sunpeek_exampledata-0.1.2.dist-info/LICENSE
sunpeek_exampledata-0.1.2.dist-info/METADATA
sunpeek_exampledata-0.1.2.dist-info/WHEEL
sunpeek_exampledata-0.1.2.dist-info/RECORD
