Metadata-Version: 2.1
Name: sunpeek-exampledata
Version: 0.1.2
Summary: Sample data for demonstration of the sunpeek solar thermal performance assessment tool
License: CC-BY-SA-4.0
Author: Philip Ohnewein, Daniel Tschopp, Lukas Feierl, Marnoch Hamilton-Jones
Maintainer: Philip Ohnewein
Maintainer-email: p.ohnewein@aee.at
Requires-Python: >=3,<4
Classifier: License :: Free To Use But Restricted
Classifier: License :: Other/Proprietary License
Classifier: Programming Language :: Python :: 3
Classifier: Programming Language :: Python :: 3.4
Classifier: Programming Language :: Python :: 3.5
Classifier: Programming Language :: Python :: 3.6
Classifier: Programming Language :: Python :: 3.7
Classifier: Programming Language :: Python :: 3.8
Classifier: Programming Language :: Python :: 3.9
Classifier: Programming Language :: Python :: 3.10
Classifier: Programming Language :: Python :: 3.11
